pyaln/__init__.py
pyaln/alignment.py
pyaln/sequtils.py
pyaln-0.1.4.dist-info/LICENSE
pyaln-0.1.4.dist-info/METADATA
pyaln-0.1.4.dist-info/WHEEL
pyaln-0.1.4.dist-info/top_level.txt
pyaln-0.1.4.dist-info/RECORD
