Metadata-Version: 2.1
Name: pyaln
Version: 0.1.4
Summary: Read, process, write multiple sequence alignments in Python
Home-page: https://github.com/marco-mariotti/pyaln
Author: Marco Mariotti
Author-email: marco.mariotti@ub.edu
License: UNKNOWN
Platform: UNKNOWN
Classifier: Programming Language :: Python :: 3
Classifier: License :: OSI Approved :: MIT License
Classifier: Operating System :: OS Independent
Requires-Python: >=3.6
License-File: LICENSE
Requires-Dist: biopython (>=1.46)
Requires-Dist: pandas (>=1.2)
Requires-Dist: numpy (>=1.16)
